tello_modules/__init__.py
tello_modules/common.py
tello_modules/laser/__init__.py
tello_modules/sensor/__init__.py
Tello_modules-0.2.dist-info/METADATA
Tello_modules-0.2.dist-info/WHEEL
Tello_modules-0.2.dist-info/top_level.txt
Tello_modules-0.2.dist-info/RECORD
